LICENSE
README.md
setup.py
src/matchfarm/Config.py
src/matchfarm/Download.py
src/matchfarm/DownloadController.py
src/matchfarm/Ingestor.py
src/matchfarm/LoadDynamoDB.py
src/matchfarm/LoadS3.py
src/matchfarm/LocalDownload.py
src/matchfarm/__init__.py
src/matchfarm/config.py
src/matchfarm/download.py
src/matchfarm/ingestor.py
src/matchfarm.egg-info/PKG-INFO
src/matchfarm.egg-info/SOURCES.txt
src/matchfarm.egg-info/dependency_links.txt
src/matchfarm.egg-info/requires.txt
src/matchfarm.egg-info/top_level.txt