Metadata-Version: 2.1
Name: matchfarm
Version: 0.1.10
Summary: Farm LOL matches
Home-page: https://github.com/cvache/LeagueMatchFarm
Author: Carson Vache
Author-email: carsonvache@gmail.com
License: GNU GENERAL PUBLIC LICENSE
Platform: UNKNOWN
Classifier: Programming Language :: Python :: 3.8
Classifier: Operating System :: OS Independent
Requires-Python: >=3.7
License-File: LICENSE
